puff_web/__init__.py
puff_web/cli.py
puff_web/initializer.py
puff_web/jquery.js
puff_web/pcli.py
puff_web-1.0.7.dist-info/LICENSE
puff_web-1.0.7.dist-info/METADATA
puff_web-1.0.7.dist-info/WHEEL
puff_web-1.0.7.dist-info/entry_points.txt
puff_web-1.0.7.dist-info/top_level.txt
puff_web-1.0.7.dist-info/RECORD
