Metadata-Version: 2.2
Name: puff-web
Version: 1.0.7
Summary: Инструмент для быстрого развёртывания веб-приложений на стеке PeeWee + MySQL + FastAPI + Jinja2 + JQuery
Home-page: https://github.com/Nemeeza/Puff
Author: Nemeeza
Author-email: demo@qnro.ru
Classifier: Programming Language :: Python :: 3
Classifier: License :: OSI Approved :: MIT License
Classifier: Operating System :: OS Independent
Requires-Python: >=3.10
License-File: LICENSE
Requires-Dist: fastapi>=0.68.0
Requires-Dist: peewee>=3.14.0
Requires-Dist: jinja2>=3.0.0
Requires-Dist: mysql-connector-python>=8.0.0
Requires-Dist: uvicorn>=0.15.0
Dynamic: author
Dynamic: author-email
Dynamic: classifier
Dynamic: description
Dynamic: description-content-type
Dynamic: home-page
Dynamic: requires-dist
Dynamic: requires-python
Dynamic: summary
